solidity_test/__init__.py
solidity_test/core.py
solidity_test-0.1.1.dist-info/METADATA
solidity_test-0.1.1.dist-info/WHEEL
solidity_test-0.1.1.dist-info/top_level.txt
solidity_test-0.1.1.dist-info/RECORD
