Metadata-Version: 2.4
Name: Solidity_test
Version: 0.1.1
Summary: Octobizteam IT Developer Technical Test
Author: masbro
Requires-Python: >=3.6
Requires-Dist: requests>=2.0.0
Dynamic: author
Dynamic: requires-dist
Dynamic: requires-python
Dynamic: summary
